wplogin/__init__.py
wplogin/wplogin.py
wplogin-0.0.1.dist-info/LICENSE.txt
wplogin-0.0.1.dist-info/METADATA
wplogin-0.0.1.dist-info/WHEEL
wplogin-0.0.1.dist-info/top_level.txt
wplogin-0.0.1.dist-info/RECORD
