Metadata-Version: 2.1
Name: wplogin
Version: 0.0.1
Summary: A Simple WordPress Login Modul
Home-page: UNKNOWN
Author: GreenWorld Dev
Author-email: coding@greenworlddev.com
License: MIT-License
Keywords: wp,wordpress,login
Platform: UNKNOWN
License-File: LICENSE.txt
